dataspree/pfnc/decoder_registry.pyi
dataspree/pfnc/exceptions.pyi
dataspree/pfnc/pixel_format.pyi
dataspree/pfnc/_internal/registry.pyi
dataspree/pfnc/_internal/utils.pyi
dataspree/pfnc/genicam/components.pyi
dataspree/pfnc/genicam/data_types.pyi
dataspree/pfnc/genicam/interface_specifics.pyi
dataspree/pfnc/genicam/number_of_bits.pyi
dataspree/pfnc/genicam/packing_types.pyi
dataspree/pfnc/genicam/pixel_format.pyi
dataspree/pfnc/__about__.py
dataspree/pfnc/__init__.py
dataspree/pfnc/py.typed
dataspree/pfnc/_internal/__init__.py
dataspree/pfnc/genicam/__init__.py
dataspree/pfnc/decoder_registry.cp311-win_amd64.pyd
dataspree/pfnc/exceptions.cp311-win_amd64.pyd
dataspree/pfnc/pixel_format.cp311-win_amd64.pyd
dataspree/pfnc/_internal/registry.cp311-win_amd64.pyd
dataspree/pfnc/_internal/utils.cp311-win_amd64.pyd
dataspree/pfnc/genicam/components.cp311-win_amd64.pyd
dataspree/pfnc/genicam/data_types.cp311-win_amd64.pyd
dataspree/pfnc/genicam/interface_specifics.cp311-win_amd64.pyd
dataspree/pfnc/genicam/number_of_bits.cp311-win_amd64.pyd
dataspree/pfnc/genicam/packing_types.cp311-win_amd64.pyd
dataspree/pfnc/genicam/pixel_format.cp311-win_amd64.pyd
pfnc-0.1.1.dist-info/METADATA
pfnc-0.1.1.dist-info/WHEEL
pfnc-0.1.1.dist-info/licenses/LICENSE.txt
pfnc-0.1.1.dist-info/RECORD
