Metadata-Version: 2.4
Name: pfnc
Version: 0.1.1
Summary: Parse and model GenICam PFNC pixel format designations and decode image buffers via extensible decoders.
Project-URL: Homepage, https://www.data-spree.com/
Project-URL: Documentation, https://github.com/dataspree/pfnc.git
Project-URL: Repository, https://github.com/dataspree/pfnc.git
Author-email: Data Spree GmbH <info@data-spree.com>
License: MIT License
License-File: LICENSE.txt
Keywords: binary-format,buffer-decoding,camera,dataspree,genicam,gig-e-vision,image-decoding,industrial-camera,machine-vision,numpy,parsing,pfnc,pixel-format
Requires-Python: >=3.10
Requires-Dist: numpy<3,>=1.24
Requires-Dist: typing-extensions>=4
